{"total": 48, "filters": "{\"PriceArea\": [\"DK1\", \"DK2\"]}", "sort": "HourDK", "limit": 0, "dataset": "Elspotprices", "records": [{"HourUTC": "2025-02-18T23:00:00", "HourDK": "2025-02-19T00:00:00", "PriceArea": "DK1", "SpotPriceDKK": 779.742959, "SpotPriceEUR": 104.540001}, {"HourUTC": "2025-02-18T23:00:00", "HourDK": "2025-02-19T00:00:00", "PriceArea": "DK2", "SpotPriceDKK": 779.742959, "SpotPriceEUR": 104.540001}, {"HourUTC": "2025-02-19T00:00:00", "HourDK": "2025-02-19T01:00:00", "PriceArea": "DK1", "SpotPriceDKK": 740.584259, "SpotPriceEUR": 99.290001}, {"HourUTC": "2025-02-19T00:00:00", "HourDK": "2025-02-19T01:00:00", "PriceArea": "DK2", "SpotPriceDKK": 740.584259, "SpotPriceEUR": 99.290001}, {"HourUTC": "2025-02-19T01:00:00", "HourDK": "2025-02-19T02:00:00", "PriceArea": "DK1", "SpotPriceDKK": 742.896465, "SpotPriceEUR": 99.599998}, {"HourUTC": "2025-02-19T01:00:00", "HourDK": "2025-02-19T02:00:00", "PriceArea": "DK2", "SpotPriceDKK": 742.896465, "SpotPriceEUR": 99.599998}, {"HourUTC": "2025-02-19T02:00:00", "HourDK": "2025-02-19T03:00:00", "PriceArea": "DK1", "SpotPriceDKK": 725.666659, "SpotPriceEUR": 97.290001}, {"HourUTC": "2025-02-19T02:00:00", "HourDK": "2025-02-19T03:00:00", "PriceArea": "DK2", "SpotPriceDKK": 725.741262, "SpotPriceEUR": 97.300003}, {"HourUTC": "2025-02-19T03:00:00", "HourDK": "2025-02-19T04:00:00", "PriceArea": "DK1", "SpotPriceDKK": 704.8566, "SpotPriceEUR": 94.5}, {"HourUTC": "2025-02-19T03:00:00", "HourDK": "2025-02-19T04:00:00", "PriceArea": "DK2", "SpotPriceDKK": 704.8566, "SpotPriceEUR": 94.5}, {"HourUTC": "2025-02-19T04:00:00", "HourDK": "2025-02-19T05:00:00", "PriceArea": "DK1", "SpotPriceDKK": 727.083846, "SpotPriceEUR": 97.480003}, {"HourUTC": "2025-02-19T04:00:00", "HourDK": "2025-02-19T05:00:00", "PriceArea": "DK2", "SpotPriceDKK": 727.158397, "SpotPriceEUR": 97.489998}, {"HourUTC": "2025-02-19T05:00:00", "HourDK": "2025-02-19T06:00:00", "PriceArea": "DK1", "SpotPriceDKK": 857.762, "SpotPriceEUR": 115.0}, {"HourUTC": "2025-02-19T05:00:00", "HourDK": "2025-02-19T06:00:00", "PriceArea": "DK2", "SpotPriceDKK": 848.289346, "SpotPriceEUR": 113.730003}, {"HourUTC": "2025-02-19T06:00:00", "HourDK": "2025-02-19T07:00:00", "PriceArea": "DK1", "SpotPriceDKK": 1115.0906, "SpotPriceEUR": 149.5}, {"HourUTC": "2025-02-19T06:00:00", "HourDK": "2025-02-19T07:00:00", "PriceArea": "DK2", "SpotPriceDKK": 1150.370694, "SpotPriceEUR": 154.229996}, {"HourUTC": "2025-02-19T07:00:00", "HourDK": "2025-02-19T08:00:00", "PriceArea": "DK1", "SpotPriceDKK": 1240.920519, "SpotPriceEUR": 166.369995}, {"HourUTC": "2025-02-19T07:00:00", "HourDK": "2025-02-19T08:00:00", "PriceArea": "DK2", "SpotPriceDKK": 1280.377638, "SpotPriceEUR": 171.660004}, {"HourUTC": "2025-02-19T08:00:00", "HourDK": "2025-02-19T09:00:00", "PriceArea": "DK1", "SpotPriceDKK": 960.395051, "SpotPriceEUR": 128.759995}, {"HourUTC": "2025-02-19T08:00:00", "HourDK": "2025-02-19T09:00:00", "PriceArea": "DK2", "SpotPriceDKK": 960.395051, "SpotPriceEUR": 128.759995}, {"HourUTC": "2025-02-19T09:00:00", "HourDK": "2025-02-19T10:00:00", "PriceArea": "DK1", "SpotPriceDKK": 804.879138, "SpotPriceEUR": 107.910004}, {"HourUTC": "2025-02-19T09:00:00", "HourDK": "2025-02-19T10:00:00", "PriceArea": "DK2", "SpotPriceDKK": 804.804535, "SpotPriceEUR": 107.900002}, {"HourUTC": "2025-02-19T10:00:00", "HourDK": "2025-02-19T11:00:00", "PriceArea": "DK1", "SpotPriceDKK": 665.921657, "SpotPriceEUR": 89.279999}, {"HourUTC": "2025-02-19T10:00:00", "HourDK": "2025-02-19T11:00:00", "PriceArea": "DK2", "SpotPriceDKK": 665.996259, "SpotPriceEUR": 89.290001}, {"HourUTC": "2025-02-19T11:00:00", "HourDK": "2025-02-19T12:00:00", "PriceArea": "DK1", "SpotPriceDKK": 608.041354, "SpotPriceEUR": 81.519997}, {"HourUTC": "2025-02-19T11:00:00", "HourDK": "2025-02-19T12:00:00", "PriceArea": "DK2", "SpotPriceDKK": 608.190559, "SpotPriceEUR": 81.540001}, {"HourUTC": "2025-02-19T12:00:00", "HourDK": "2025-02-19T13:00:00", "PriceArea": "DK1", "SpotPriceDKK": 617.141097, "SpotPriceEUR": 82.739998}, {"HourUTC": "2025-02-19T12:00:00", "HourDK": "2025-02-19T13:00:00", "PriceArea": "DK2", "SpotPriceDKK": 617.290303, "SpotPriceEUR": 82.760002}, {"HourUTC": "2025-02-19T13:00:00", "HourDK": "2025-02-19T14:00:00", "PriceArea": "DK1", "SpotPriceDKK": 635.489738, "SpotPriceEUR": 85.199997}, {"HourUTC": "2025-02-19T13:00:00", "HourDK": "2025-02-19T14:00:00", "PriceArea": "DK2", "SpotPriceDKK": 635.489738, "SpotPriceEUR": 85.199997}, {"HourUTC": "2025-02-19T14:00:00", "HourDK": "2025-02-19T15:00:00", "PriceArea": "DK1", "SpotPriceDKK": 675.991022, "SpotPriceEUR": 90.629997}, {"HourUTC": "2025-02-19T14:00:00", "HourDK": "2025-02-19T15:00:00", "PriceArea": "DK2", "SpotPriceDKK": 663.982354, "SpotPriceEUR": 89.019997}, {"HourUTC": "2025-02-19T15:00:00", "HourDK": "2025-02-19T16:00:00", "PriceArea": "DK1", "SpotPriceDKK": 820.691757, "SpotPriceEUR": 110.029999}, {"HourUTC": "2025-02-19T15:00:00", "HourDK": "2025-02-19T16:00:00", "PriceArea": "DK2", "SpotPriceDKK": 832.849638, "SpotPriceEUR": 111.660004}, {"HourUTC": "2025-02-19T16:00:00", "HourDK": "2025-02-19T17:00:00", "PriceArea": "DK1", "SpotPriceDKK": 979.191257, "SpotPriceEUR": 131.279999}, {"HourUTC": "2025-02-19T16:00:00", "HourDK": "2025-02-19T17:00:00", "PriceArea": "DK2", "SpotPriceDKK": 979.2658, "SpotPriceEUR": 131.289993}, {"HourUTC": "2025-02-19T17:00:00", "HourDK": "2025-02-19T18:00:00", "PriceArea": "DK1", "SpotPriceDKK": 1066.459194, "SpotPriceEUR": 142.979996}, {"HourUTC": "2025-02-19T17:00:00", "HourDK": "2025-02-19T18:00:00", "PriceArea": "DK2", "SpotPriceDKK": 1087.045549, "SpotPriceEUR": 145.740005}, {"HourUTC": "2025-02-19T18:00:00", "HourDK": "2025-02-19T19:00:00", "PriceArea": "DK1", "SpotPriceDKK": 1016.783668, "SpotPriceEUR": 136.320007}, {"HourUTC": "2025-02-19T18:00:00", "HourDK": "2025-02-19T19:00:00", "PriceArea": "DK2", "SpotPriceDKK": 1056.837387, "SpotPriceEUR": 141.690002}, {"HourUTC": "2025-02-19T19:00:00", "HourDK": "2025-02-19T20:00:00", "PriceArea": "DK1", "SpotPriceDKK": 846.797557, "SpotPriceEUR": 113.529999}, {"HourUTC": "2025-02-19T19:00:00", "HourDK": "2025-02-19T20:00:00", "PriceArea": "DK2", "SpotPriceDKK": 901.843538, "SpotPriceEUR": 120.910004}, {"HourUTC": "2025-02-19T20:00:00", "HourDK": "2025-02-19T21:00:00", "PriceArea": "DK1", "SpotPriceDKK": 736.034384, "SpotPriceEUR": 98.68}, {"HourUTC": "2025-02-19T20:00:00", "HourDK": "2025-02-19T21:00:00", "PriceArea": "DK2", "SpotPriceDKK": 848.513103, "SpotPriceEUR": 113.760002}, {"HourUTC": "2025-02-19T21:00:00", "HourDK": "2025-02-19T22:00:00", "PriceArea": "DK1", "SpotPriceDKK": 654.5097, "SpotPriceEUR": 87.75}, {"HourUTC": "2025-02-19T21:00:00", "HourDK": "2025-02-19T22:00:00", "PriceArea": "DK2", "SpotPriceDKK": 799.061222, "SpotPriceEUR": 107.129997}, {"HourUTC": "2025-02-19T22:00:00", "HourDK": "2025-02-19T23:00:00", "PriceArea": "DK1", "SpotPriceDKK": 605.356238, "SpotPriceEUR": 81.160004}, {"HourUTC": "2025-02-19T22:00:00", "HourDK": "2025-02-19T23:00:00", "PriceArea": "DK2", "SpotPriceDKK": 613.933813, "SpotPriceEUR": 82.309998}]}